Workbook

Sheet Cover
B2: TransUnion DCF Model
B5: Functional DCF built from FY2023-FY2025 actuals, 2026 management guidance, and explicitly labeled analyst assumptions.
B7: • Historicals are sourced from SEC filings; management's 2026 guide anchors the first forecast year.
B8: • WACC is built from Damodaran's April 1, 2026 U.S. ERP update, market-derived beta, and TRU cost of debt.
B9: • Sensitivities show implied per-share value across WACC and terminal growth combinations.

Sheet Instructions
B2: Model Flow
B4: 1 | C4: Use Assumptions to inspect market inputs, capital costs, and forecast drivers.
B6: 2 | C6: Model contains historical actuals and formula-linked forecast lines.
B8: 3 | C8: Valuation and Sensitivities are print-ready summary tabs for interview or portfolio use.

Sheet Assumptions
B2: Valuation Inputs
B4: Valuation Date | C4: 2026-04-01
B5: Share Price | C5: 68.790001
B6: Shares Outstanding (mm) | C6: 192.6
B7: Cash ($mm) | C7: 853.6
B8: Debt ($mm) | C8: 5035.9
B9: Risk-Free Rate | C9: 0.0432
B10: Levered Beta | C10: 1.56
B11: Equity Risk Premium | C11: 0.0467
B12: Cost of Equity | C12: 0.116052
B13: Pre-tax Cost of Debt | C13: 0.046324309
B14: Tax Rate | C14: 0.25
B15: WACC | C15: 0.093658448
B16: Terminal Growth | C16: 0.025
E20: 2026 | F20: 2027 | G20: 2028 | H20: 2029 | I20: 2030
B21: Revenue Growth | E21: 0.085 | F21: 0.07 | G21: 0.06 | H21: 0.05 | I21: 0.04
B22: EBITDA Margin | E22: 0.315 | F22: 0.318 | G22: 0.32 | H22: 0.323 | I22: 0.325
B23: D&A Margin | E23: 0.12 | F23: 0.117 | G23: 0.114 | H23: 0.111 | I23: 0.108
B24: Capex Margin | E24: 0.07 | F24: 0.067 | G24: 0.065 | H24: 0.063 | I24: 0.06
B25: NWC Margin | E25: 0.094 | F25: 0.093 | G25: 0.092 | H25: 0.091 | I25: 0.09

Sheet Model
B2: Historical & Forecast Cash Flow Build ($mm)
D4: 2023 | E4: 2024 | F4: 2025 | G4: 2026 | H4: 2027 | I4: 2028 | J4: 2029 | K4: 2030
B5: Revenue | D5: 3831.2 | E5: 4183.8 | F5: 4576.3 | G5: =F5*(1+Assumptions!E21) | H5: =G5*(1+Assumptions!F21) | I5: =H5*(1+Assumptions!G21) | J5: =I5*(1+Assumptions!H21) | K5: =J5*(1+Assumptions!I21)
B6: EBITDA | D6: 652.9 | E6: 1204.5 | F6: 1432.6 | G6: =G5*Assumptions!E22 | H6: =H5*Assumptions!F22 | I6: =I5*Assumptions!G22 | J6: =J5*Assumptions!H22 | K6: =K5*Assumptions!I22
B7: D&A | D7: 524.4 | E7: 537.8 | F7: 574.8 | G7: =G5*Assumptions!E23 | H7: =H5*Assumptions!F23 | I7: =I5*Assumptions!G23 | J7: =J5*Assumptions!H23 | K7: =K5*Assumptions!I23
B8: EBIT | D8: 128.5 | E8: 666.7 | F8: 857.8 | G8: =G6-G7 | H8: =H6-H7 | I8: =I6-I7 | J8: =J6-J7 | K8: =K6-K7
B9: Taxes | D9: 32.125 | E9: 166.675 | F9: 214.45 | G9: =G8*Assumptions!C14 | H9: =H8*Assumptions!C14 | I9: =I8*Assumptions!C14 | J9: =J8*Assumptions!C14 | K9: =K8*Assumptions!C14
B10: Capex | D10: 310.7 | E10: 315.8 | F10: 326 | G10: =G5*Assumptions!E24 | H10: =H5*Assumptions!F24 | I10: =I5*Assumptions!G24 | J10: =J5*Assumptions!H24 | K10: =K5*Assumptions!I24
B11: NWC | D11: 405.4 | E11: 388.6 | F11: 441.8 | G11: =G5*Assumptions!E25 | H11: =H5*Assumptions!F25 | I11: =I5*Assumptions!G25 | J11: =J5*Assumptions!H25 | K11: =K5*Assumptions!I25
B12: Change in NWC | D12: 0 | E12: -16.8 | F12: 53.2 | G12: =G11-F11 | H12: =H11-G11 | I12: =I11-H11 | J12: =J11-I11 | K12: =K11-J11
B13: UFCF | D13: 310.075 | E13: 738.825 | F13: 838.95 | G13: =G8-G9+G7-G10-G12 | H13: =H8-H9+H7-H10-H12 | I13: =I8-I9+I7-I10-I12 | J13: =J8-J9+J7-J10-J12 | K13: =K8-K9+K7-K10-K12

Sheet Valuation
B2: DCF Valuation
D4: 2026 | E4: 2027 | F4: 2028 | G4: 2029 | H4: 2030
B5: UFCF | D5: =Model!G13 | E5: =Model!H13 | F5: =Model!I13 | G5: =Model!J13 | H5: =Model!K13
B6: Discount Factor | D6: =1/((1+Assumptions!C15)^1) | E6: =1/((1+Assumptions!C15)^2) | F6: =1/((1+Assumptions!C15)^3) | G6: =1/((1+Assumptions!C15)^4) | H6: =1/((1+Assumptions!C15)^5)
B7: PV of UFCF | D7: =D5*D6 | E7: =E5*E6 | F7: =F5*F6 | G7: =G5*G6 | H7: =H5*H6
B10: Terminal Value | C10: =H5*(1+Assumptions!C16)/(Assumptions!C15-Assumptions!C16)
B11: PV of Terminal Value | C11: =C10*H6
B12: Enterprise Value | C12: =SUM(C7:G7)+C11
B13: Less: Debt | C13: =Assumptions!C8
B14: Add: Cash | C14: =Assumptions!C7
B15: Equity Value | C15: =C12-C13+C14
B16: Implied Share Price | C16: =C15/Assumptions!C6
B17: Premium / (Discount) to Current Price | C17: =C16/Assumptions!C5-1

Sheet Sensitivities
B2: Share Price Sensitivity
D4: 0.0837 | E4: 0.0887 | F4: 0.0937 | G4: 0.0987 | H4: 0.1037
B5: 0.02 | D5: 72.223488 | E5: 65.226327 | F5: 59.181172 | G5: 53.906517 | H5: 49.264229
B6: 0.0225 | D6: 75.315193 | E6: 67.828149 | F6: 61.395209 | G6: 55.808817 | H6: 50.912542
B7: 0.025 | D7: 78.670247 | E7: 70.634196 | F7: 63.770384 | G7: 57.840174 | H7: 52.665575
B8: 0.0275 | D8: 82.323792 | E8: 73.669495 | F8: 66.324953 | G8: 60.014183 | H8: 54.533638
B9: 0.03 | D9: 86.317519 | E9: 76.963337 | F9: 69.080038 | G9: 62.346416 | H9: 56.528434

Sheet Output
B2: DCF Output
B4: Enterprise Value | C4: =Valuation!C12
B5: Equity Value | C5: =Valuation!C15
B6: Implied Share Price | C6: =Valuation!C16
B7: Current Share Price | C7: =Assumptions!C5
B8: Premium / (Discount) | C8: =Valuation!C17

Sheet Checks
B2: Checks & Audit
B4: Check | C4: Status
B5: WACC is above terminal growth | C5: =IF(Assumptions!C15>Assumptions!C16,"OK","CHECK")
B6: Discount factor row declines over time | C6: =IF(AND(Valuation!D6<Valuation!C6,Valuation!H6<Valuation!G6),"OK","CHECK")
B7: Implied share price is numeric | C7: =IF(ISNUMBER(Valuation!C16),"OK","CHECK")

Sheet Source_Notes
B2: Source Notes
B4: Category | C4: Entity | D4: Document | E4: As of | F4: URL | G4: Local File | H4: Notes
B5: DCF | C5: TransUnion | D5: 2025 10-K | E5: 2025-12-31 | F5: https://www.sec.gov/Archives/edgar/data/1552033/000155203326000012/tru-20251231.htm | G5: data/raw/reference_html/tru_2025_10k.html | H5: Historical actuals and balance-sheet data.
B6: DCF | C6: TransUnion | D6: 2026 Earnings Release | E6: 2026-02-12 | F6: https://www.sec.gov/Archives/edgar/data/1552033/000155203326000006/exhibit99112312025.htm | G6: data/raw/reference_html/tru_2026_guidance.html | H6: Management 2026 revenue and adjusted EBITDA guidance.
B7: Valuation | C7: Damodaran | D7: Implied ERP Update | E7: 2026-04-01 | F7: https://pages.stern.nyu.edu/~adamodar/New_Home_Page/home.htm | G7: data/raw/reference_html/damodaran_home_apr_2026.html | H7: Used for U.S. ERP and risk-free rate assumptions.
