Workbook

Sheet Cover
B2: TransUnion 3-Statement Workflow | Full Track
B5: Full-track build with explicit IS, BS, CF, and balance-bridge logic.
B7: • The model separates assumptions, statements, schedules, summary outputs, and checks.
B8: • Forecasts roll through the income statement, selected balance-sheet lines, and cash build.
B9: • This workbook intentionally bridges into the full DCF module.

Sheet Instructions
B2: Build Sequence
B4: 1 | C4: Work from Build_Map, then Assumptions, IS, Schedules, CF, and BS in order.
B6: 2 | C6: The full-track file adds an actual balance sheet and cash flow statement that must tie.
B8: 3 | C8: Use Summary and Checks only after the balance check is at or near zero.

Sheet Build_Map
B2: Full Track Build Map
B3: Sheet | C3: Purpose | D3: What You Build
B4: Assumptions | C4: Forecast inputs | D4: Revenue growth, margins, capex, and NWC assumptions.
B5: IS | C5: Income statement | D5: Forecast EBIT, taxes, and net income.
B6: Schedules | C6: Operating support | D6: NWC, capex, and FCF-before-financing support.
B7: CF | C7: Cash flow statement | D7: Walk net income to ending cash.
B8: BS | C8: Balance sheet | D8: Roll cash, debt, equity, and net operating assets to a balance check.
B9: Summary | C9: Output | D9: Surface the key operating and balance outputs.
B10: Checks | C10: Audit | D10: Confirm the model ties and remains populated.

Sheet Assumptions
B2: Forecast Drivers
D4: 2026 | E4: 2027 | F4: 2028
B5: Revenue Growth | D5: 0.085 | E5: 0.07 | F5: 0.06
B6: EBITDA Margin | D6: 0.315 | E6: 0.318 | F6: 0.32
B7: D&A Margin | D7: 0.12 | E7: 0.117 | F7: 0.114
B8: Capex Margin | D8: 0.07 | E8: 0.067 | F8: 0.065
B9: NWC Margin | D9: 0.094 | E9: 0.093 | F9: 0.092

Sheet IS
B2: Income Statement ($mm)
D4: 2023 | E4: 2024 | F4: 2025 | G4: 2026 | H4: 2027 | I4: 2028
B5: Revenue | D5: 3831.2 | E5: 4183.8 | F5: 4576.3 | G5: =F5*(1+Assumptions!G5) | H5: =G5*(1+Assumptions!H5) | I5: =H5*(1+Assumptions!I5)
B6: EBITDA | D6: 652.9 | E6: 1204.5 | F6: 1432.6 | G6: =G5*Assumptions!G6 | H6: =H5*Assumptions!H6 | I6: =I5*Assumptions!I6
B7: D&A | D7: 524.4 | E7: 537.8 | F7: 574.8 | G7: =G5*Assumptions!G7 | H7: =H5*Assumptions!H7 | I7: =I5*Assumptions!I7
B8: EBIT | D8: 128.5 | E8: 666.7 | F8: 857.8 | G8: =G6-G7 | H8: =H6-H7 | I8: =I6-I7
B9: Interest | D9: 288.2 | E9: 265.2 | F9: 235.8 | G9: =F9 | H9: =F9 | I9: =F9
B10: Pretax Income | D10: -159.7 | E10: 401.5 | F10: 622 | G10: =G8-G9 | H10: =H8-H9 | I10: =I8-I9
B11: Taxes | D11: -39.925 | E11: 100.375 | F11: 155.5 | G11: =G10*0.25 | H11: =H10*0.25 | I11: =I10*0.25
B12: Net Income | D12: -190.8 | E12: 302.3 | F12: 469.9 | G12: =G10-G11 | H12: =H10-H11 | I12: =I10-I11

Sheet Schedules
B2: Operating Support Schedules ($mm)
D4: 2023 | E4: 2024 | F4: 2025 | G4: 2026 | H4: 2027 | I4: 2028
B5: NWC | D5: 405.4 | E5: 388.6 | F5: 441.8 | G5: =IS!G5*Assumptions!G9 | H5: =IS!H5*Assumptions!H9 | I5: =IS!I5*Assumptions!I9
B6: Change in NWC | D6: 0 | E6: -16.8 | F6: 53.2 | G6: =G5-F5 | H6: =H5-G5 | I6: =I5-H5
B7: Capex | D7: 310.7 | E7: 315.8 | F7: 326 | G7: =IS!G5*Assumptions!G8 | H7: =IS!H5*Assumptions!H8 | I7: =IS!I5*Assumptions!I8
B8: FCF Before Financing | D8: 22.9 | E8: 541.1 | F8: 665.5 | G8: =IS!G12+IS!G7-G7-G6 | H8: =IS!H12+IS!H7-H7-H6 | I8: =IS!I12+IS!I7-I7-I6

Sheet CF
B2: Cash Flow Statement ($mm)
D4: 2023 | E4: 2024 | F4: 2025 | G4: 2026 | H4: 2027 | I4: 2028
B5: Net Income | D5: -190.8 | E5: 302.3 | F5: 469.9 | G5: =IS!G12 | H5: =IS!H12 | I5: =IS!I12
B6: D&A | D6: 524.4 | E6: 537.8 | F6: 574.8 | G6: =IS!G7 | H6: =IS!H7 | I6: =IS!I7
B7: Capex | D7: -310.7 | E7: -315.8 | F7: -326 | G7: =-Schedules!G7 | H7: =-Schedules!H7 | I7: =-Schedules!I7
B8: Change in NWC | D8: 0 | E8: 16.8 | F8: -53.2 | G8: =-Schedules!G6 | H8: =-Schedules!H6 | I8: =-Schedules!I6
B9: Cash Flow Before Financing | D9: 22.9 | E9: 541.1 | F9: 665.5 | G9: =SUM(G5:G8) | H9: =SUM(H5:H8) | I9: =SUM(I5:I8)
B10: Change in Debt | D10: 0 | E10: 0 | F10: 0 | G10: 0 | H10: 0 | I10: 0
B11: Change in Cash | D11: 22.9 | E11: 541.1 | F11: 665.5 | G11: =G9+G10 | H11: =H9+H10 | I11: =I9+I10
B12: Beginning Cash | D12: 453.3 | E12: 138.4 | F12: 188.1 | G12: =F13 | H12: =G13 | I12: =H13
B13: Ending Cash | D13: 476.2 | E13: 679.5 | F13: 853.6 | G13: =G12+G11 | H13: =H12+H11 | I13: =I12+I11

Sheet BS
B2: Balance Sheet ($mm)
D4: 2023 | E4: 2024 | F4: 2025 | G4: 2026 | H4: 2027 | I4: 2028
B5: Cash | D5: 476.2 | E5: 679.5 | F5: 853.6 | G5: =CF!G13 | H5: =CF!H13 | I5: =CF!I13
B6: Net Working Capital | D6: 405.4 | E6: 388.6 | F6: 441.8 | G6: =Schedules!G5 | H6: =Schedules!H5 | I6: =Schedules!I5
B7: Net Operating Assets | D7: 10223.5 | E7: 9916.7 | F7: 9817.5 | G7: =F7+Schedules!G7-IS!G7 | H7: =G7+Schedules!H7-IS!H7 | I7: =H7+Schedules!I7-IS!I7
B8: Total Assets | D8: 11105.1 | E8: 10984.8 | F8: 11112.9 | G8: =SUM(G5:G7) | H8: =SUM(H5:H7) | I8: =SUM(I5:I7)
B10: Debt | D10: 5250.8 | E10: 5076.6 | F10: 5103.8 | G10: =F10 | H10: =G10 | I10: =H10
B11: Other Liabilities | D11: 1748.8 | E11: 1589.4 | F11: 1463.8 | G11: =F11 | H11: =G11 | I11: =H11
B12: Equity | D12: 4008.2 | E12: 4217 | F12: 4439.2 | G12: =F12+IS!G12 | H12: =G12+IS!H12 | I12: =H12+IS!I12
B13: Total Liabilities & Equity | D13: 11007.8 | E13: 10883 | F13: 11006.8 | G13: =SUM(G10:G12) | H13: =SUM(H10:H12) | I13: =SUM(I10:I12)
B14: Balance Check | D14: 0 | E14: 0 | F14: 0 | G14: =G8-G13 | H14: =H8-H13 | I14: =I8-I13

Sheet Summary
B2: Analyst Summary | Full Track
B4: 2026 Revenue | C4: =IS!G5
B5: 2026 EBITDA | C5: =IS!G6
B6: 2026 Ending Cash | C6: =BS!G5
B7: 2028 Ending Cash | C7: =BS!I5
B8: 2028 Balance Check | C8: =BS!I14

Sheet Checks
B2: Checks & Audit
B4: Check | C4: Status
B5: Forecast ending cash rolls from the cash flow statement into the balance sheet | C5: =IF(ABS(BS!I5-CF!I13)<0.1,"OK","CHECK")
B6: Full-track balance check is at or near zero in 2028 | C6: =IF(ABS(BS!I14)<0.1,"OK","CHECK")
B7: Net income line is populated for forecast years | C7: =IF(COUNT(IS!G12:I12)=3,"OK","CHECK")
B8: Ending cash remains positive through the forecast | C8: =IF(MIN(BS!G5:I5)>0,"OK","CHECK")

Sheet Source_Notes
B2: Source Notes
B4: Category | C4: Entity | D4: Document | E4: As of | F4: URL | G4: Local File | H4: Notes
B5: DCF | C5: TransUnion | D5: 2025 10-K | E5: 2025-12-31 | F5: https://www.sec.gov/Archives/edgar/data/1552033/000155203326000012/tru-20251231.htm | G5: data/raw/reference_html/tru_2025_10k.html | H5: Historical actuals and balance-sheet data.
B6: DCF | C6: TransUnion | D6: 2026 Earnings Release | E6: 2026-02-12 | F6: https://www.sec.gov/Archives/edgar/data/1552033/000155203326000006/exhibit99112312025.htm | G6: data/raw/reference_html/tru_2026_guidance.html | H6: Management 2026 revenue and adjusted EBITDA guidance.
B7: Valuation | C7: Damodaran | D7: Implied ERP Update | E7: 2026-04-01 | F7: https://pages.stern.nyu.edu/~adamodar/New_Home_Page/home.htm | G7: data/raw/reference_html/damodaran_home_apr_2026.html | H7: Used for U.S. ERP and risk-free rate assumptions.
