Workbook

Sheet Cover
B2: Dun & Bradstreet LBO Model | Full Track
B5: Formula-driven sponsor model with linked assumptions, debt rollforward, and return outputs.
B7: • This version is built as a live model rather than a mostly pre-populated answer key.
B8: • The operating case, debt schedule, and returns all link back to centralized assumptions.
B9: • Sensitivity output is included to mirror timed analyst-test presentation standards.

Sheet Instructions
B2: Build Sequence
B4: 1 | C4: Populate Assumptions first, then audit the Transaction bridge before modeling operations.
B6: 2 | C6: Build Operating_Case, then the Debt_Schedule, then Returns and Sensitivities.
B8: 3 | C8: Treat Output as the presentation tab and Checks as the model-control tab.

Sheet Assumptions
B2: LBO Inputs
B4: Offer Price | C4: 9.15
B5: Shares Outstanding (mm) | C5: 441.51637
B6: Debt Refinancing ($mm) | C6: 3497.7
B7: Fees & Expenses ($mm) | C7: 161.9
B8: Revolver ($mm) | C8: 300
B9: Term Loan B ($mm) | C9: 3200
B10: Senior Notes ($mm) | C10: 1200
B11: Revolver Rate | C11: 0.071
B12: TLB Rate | C12: 0.076
B13: Senior Notes Rate | C13: 0.085
B14: Mandatory TLB Amortization ($mm) | C14: 32
B15: Exit Multiple | C15: 8
B16: Incremental NWC % of Sales Growth | C16: 0.005
D20: 2025 | E20: 2026 | F20: 2027 | G20: 2028 | H20: 2029 | I20: 2030
B21: Revenue Base / Growth | D21: 2470
B22: Revenue Growth | D22: 0 | E22: 0.032 | F22: 0.029 | G22: 0.026 | H22: 0.025 | I22: 0.022
B23: EBITDA Margin | D23: 0.39271255 | E23: 0.396 | F23: 0.399 | G23: 0.401 | H23: 0.403 | I23: 0.405
B24: D&A ($mm) | D24: 165 | E24: 168 | F24: 170 | G24: 172 | H24: 175 | I24: 177
B25: Capex ($mm) | D25: 195 | E25: 193 | F25: 192 | G25: 190 | H25: 188 | I25: 185
B26: Cash Tax Rate | D26: 0.225 | E26: 0.225 | F26: 0.225 | G26: 0.225 | H26: 0.225 | I26: 0.225

Sheet Transaction
B2: Sources & Uses ($mm)
B4: Equity Purchase | C4: =Assumptions!C4*Assumptions!C5 | E4: Revolver | F4: =Assumptions!C8
B5: Debt Refinancing | C5: =Assumptions!C6 | E5: Term Loan B | F5: =Assumptions!C9
B6: Fees & Expenses | C6: =Assumptions!C7 | E6: Senior Notes | F6: =Assumptions!C10
B7: Total Uses | C7: =SUM(C4:C6) | E7: Sponsor Equity | F7: =C7-SUM(F4:F6)
E8: Total Sources | F8: =SUM(F4:F7)

Sheet Operating_Case
B2: Operating Case ($mm)
D4: 2025 | E4: 2026 | F4: 2027 | G4: 2028 | H4: 2029 | I4: 2030
B5: Revenue | D5: =Assumptions!D21 | E5: =D5*(1+Assumptions!E22) | F5: =E5*(1+Assumptions!F22) | G5: =F5*(1+Assumptions!G22) | H5: =G5*(1+Assumptions!H22) | I5: =H5*(1+Assumptions!I22)
B6: Revenue Growth | D6: 0 | E6: =Assumptions!E22 | F6: =Assumptions!F22 | G6: =Assumptions!G22 | H6: =Assumptions!H22 | I6: =Assumptions!I22
B7: EBITDA Margin | D7: =Assumptions!D23 | E7: =Assumptions!E23 | F7: =Assumptions!F23 | G7: =Assumptions!G23 | H7: =Assumptions!H23 | I7: =Assumptions!I23
B8: EBITDA | D8: =D5*D7 | E8: =E5*E7 | F8: =F5*F7 | G8: =G5*G7 | H8: =H5*H7 | I8: =I5*I7
B9: D&A | D9: =Assumptions!D24 | E9: =Assumptions!E24 | F9: =Assumptions!F24 | G9: =Assumptions!G24 | H9: =Assumptions!H24 | I9: =Assumptions!I24
B10: EBIT | D10: =D8-D9 | E10: =E8-E9 | F10: =F8-F9 | G10: =G8-G9 | H10: =H8-H9 | I10: =I8-I9
B11: Cash Tax Rate | D11: =Assumptions!D26 | E11: =Assumptions!E26 | F11: =Assumptions!F26 | G11: =Assumptions!G26 | H11: =Assumptions!H26 | I11: =Assumptions!I26
B12: Cash Taxes | D12: =D10*D11 | E12: =E10*E11 | F12: =F10*F11 | G12: =G10*G11 | H12: =H10*H11 | I12: =I10*I11
B13: Capex | D13: =Assumptions!D25 | E13: =Assumptions!E25 | F13: =Assumptions!F25 | G13: =Assumptions!G25 | H13: =Assumptions!H25 | I13: =Assumptions!I25
B14: Change in NWC | D14: 0 | E14: =MAX((E5-D5)*Assumptions!C16,0) | F14: =MAX((F5-E5)*Assumptions!C16,0) | G14: =MAX((G5-F5)*Assumptions!C16,0) | H14: =MAX((H5-G5)*Assumptions!C16,0) | I14: =MAX((I5-H5)*Assumptions!C16,0)
B15: Pre-Interest FCF | D15: =D8-D12-D13-D14 | E15: =E8-E12-E13-E14 | F15: =F8-F12-F13-F14 | G15: =G8-G12-G13-G14 | H15: =H8-H12-H13-H14 | I15: =I8-I12-I13-I14

Sheet Debt_Schedule
B2: Debt Schedule ($mm)
D4: 2025 | E4: 2026 | F4: 2027 | G4: 2028 | H4: 2029 | I4: 2030
B5: Beginning Revolver | D5: =Transaction!F4 | E5: =D12 | F5: =E12 | G5: =F12 | H5: =G12 | I5: =H12
B6: Beginning TLB | D6: =Transaction!F5 | E6: =D13 | F6: =E13 | G6: =F13 | H6: =G13 | I6: =H13
B7: Beginning Notes | D7: =Transaction!F6 | E7: =D14 | F7: =E14 | G7: =F14 | H7: =G14 | I7: =H14
B8: Interest Expense | D8: =D5*Assumptions!C11+D6*Assumptions!C12+D7*Assumptions!C13 | E8: =E5*Assumptions!C11+E6*Assumptions!C12+E7*Assumptions!C13 | F8: =F5*Assumptions!C11+F6*Assumptions!C12+F7*Assumptions!C13 | G8: =G5*Assumptions!C11+G6*Assumptions!C12+G7*Assumptions!C13 | H8: =H5*Assumptions!C11+H6*Assumptions!C12+H7*Assumptions!C13 | I8: =I5*Assumptions!C11+I6*Assumptions!C12+I7*Assumptions!C13
B9: Mandatory Amortization | D9: =MIN(Assumptions!C14,D6) | E9: =MIN(Assumptions!C14,E6) | F9: =MIN(Assumptions!C14,F6) | G9: =MIN(Assumptions!C14,G6) | H9: =MIN(Assumptions!C14,H6) | I9: =MIN(Assumptions!C14,I6)
B10: Sweep to Revolver | D10: =MIN(D5,MAX(Operating_Case!D15-D8-D9,0)) | E10: =MIN(E5,MAX(Operating_Case!E15-E8-E9,0)) | F10: =MIN(F5,MAX(Operating_Case!F15-F8-F9,0)) | G10: =MIN(G5,MAX(Operating_Case!G15-G8-G9,0)) | H10: =MIN(H5,MAX(Operating_Case!H15-H8-H9,0)) | I10: =MIN(I5,MAX(Operating_Case!I15-I8-I9,0))
B11: Sweep to TLB | D11: =MIN(D6-D9,MAX(Operating_Case!D15-D8-D9-D10,0)) | E11: =MIN(E6-E9,MAX(Operating_Case!E15-E8-E9-E10,0)) | F11: =MIN(F6-F9,MAX(Operating_Case!F15-F8-F9-F10,0)) | G11: =MIN(G6-G9,MAX(Operating_Case!G15-G8-G9-G10,0)) | H11: =MIN(H6-H9,MAX(Operating_Case!H15-H8-H9-H10,0)) | I11: =MIN(I6-I9,MAX(Operating_Case!I15-I8-I9-I10,0))
B12: Ending Revolver | D12: =D5-D10 | E12: =E5-E10 | F12: =F5-F10 | G12: =G5-G10 | H12: =H5-H10 | I12: =I5-I10
B13: Ending TLB | D13: =D6-D9-D11 | E13: =E6-E9-E11 | F13: =F6-F9-F11 | G13: =G6-G9-G11 | H13: =H6-H9-H11 | I13: =I6-I9-I11
B14: Ending Notes | D14: =D7 | E14: =E7 | F14: =F7 | G14: =G7 | H14: =H7 | I14: =I7
B15: Ending Total Debt | D15: =SUM(D12:D14) | E15: =SUM(E12:E14) | F15: =SUM(F12:F14) | G15: =SUM(G12:G14) | H15: =SUM(H12:H14) | I15: =SUM(I12:I14)

Sheet Returns
B2: Returns Analysis
B4: Sponsor Equity Invested | C4: =Transaction!F7
B5: Exit EBITDA | C5: =Operating_Case!I8
B6: Exit Multiple | C6: =Assumptions!C15
B7: Exit Enterprise Value | C7: =C5*C6
B8: Less: Exit Debt | C8: =Debt_Schedule!I15
B9: Exit Equity Value | C9: =C7-C8
B10: MOIC | C10: =C9/C4
B11: 5-Year IRR | C11: =C10^(1/5)-1

Sheet Sensitivities
B2: IRR Sensitivity
D4: 4 | E4: 4.5 | F4: 5 | G4: 5.5 | H4: 6
B5: 7 | D5: 0.064152209 | E5: 0.07229826 | F5: 0.082843244 | G5: 0.097049679 | H5: 0.1172776
B6: 7.5 | D6: 0.086503773 | E6: 0.097029623 | F6: 0.11053386 | G6: 0.12852787 | H6: 0.15379533
B7: 8 | D7: 0.10715438 | E7: 0.1197131 | F7: 0.13570992 | G7: 0.1568415 | H7: 0.18620131
B8: 8.5 | D8: 0.12637017 | E8: 0.14069475 | F8: 0.15883329 | G8: 0.18262726 | H8: 0.21541008
B9: 9 | D9: 0.14435766 | E9: 0.16023742 | F9: 0.18024601 | G9: 0.20634244 | H9: 0.24205422

Sheet Output
B2: LBO Output
B4: Entry EV | C4: =Transaction!C7
B5: Sponsor Equity | C5: =Returns!C4
B6: Exit Equity Value | C6: =Returns!C9
B7: MOIC | C7: =Returns!C10
B8: IRR | C8: =Returns!C11

Sheet Checks
B2: Checks & Audit
B4: Check | C4: Status
B5: Sources equal uses | C5: =IF(ABS(Transaction!C7-Transaction!F8)<0.1,"OK","CHECK")
B6: Debt declines by exit year | C6: =IF(Debt_Schedule!I15<Debt_Schedule!D15,"OK","CHECK")
B7: IRR output is numeric | C7: =IF(ISNUMBER(Returns!C11),"OK","CHECK")
B8: Operating case produces positive EBITDA every year | C8: =IF(MIN(Operating_Case!D8:I8)>0,"OK","CHECK")

Sheet Source_Notes
B2: Source Notes
B4: Category | C4: Entity | D4: Document | E4: As of | F4: URL | G4: Local File | H4: Notes
B5: LBO | C5: Dun & Bradstreet | D5: 2024 10-K | E5: 2024-12-31 | F5: https://www.sec.gov/Archives/edgar/data/1799208/000179920825000012/dnb-20241231.htm | G5: data/raw/reference_html/dnb_2024_10k.html | H5: Historical GAAP actuals and capital structure.
B6: LBO | C6: Dun & Bradstreet | D6: Q4 2024 Earnings Presentation | E6: 2025-02-20 | F6: https://www.sec.gov/Archives/edgar/data/1799208/000179920825000008/dbearningspresentationq4.htm | G6: data/raw/reference_html/dnb_2025_guidance.html | H6: Management 2025 revenue, EBITDA, D&A, tax, and capex guidance.
B7: LBO | C7: Dun & Bradstreet | D7: Acquisition Announcement | E7: 2025-03-24 | F7: https://www.sec.gov/Archives/edgar/data/1799208/000110465925027293/tm2510133d1_ex99-1.htm | G7: data/raw/reference_html/dnb_deal_announcement.html | H7: Offer price and headline transaction valuation.
