Workbook

Sheet Cover
B2: Information & Data Services Trading Comps
B5: Public-peer valuation set built off FY2025 SEC filings and market data as of April 1, 2026.
B7: • Universe selected for recurring data, analytics, credit, and benchmark businesses.
B8: • LTM metrics use FY2025 reported financials because all selected peers have December year ends.
B9: • Outputs follow a banker-style trading comps summary with medians, means, and presentation-ready multiples.

Sheet Instructions
B2: How To Use This Workbook
B4: 1 | C4: Review the peer rationale on Universe before changing the basket.
B6: 2 | C6: Refresh market data with the scripts if you want to roll the valuation date.
B8: 3 | C8: Use Output for presentation tables; keep Market_Data as the supporting working tab.

Sheet Universe
B2: Peer Universe
B3: Ticker | C3: Company | D3: Inclusion Rationale
B4: MORN | C4: Morningstar | D4: investment research and wealth technology
B5: TRU | C5: TransUnion | D5: credit bureau, fraud, and identity data
B6: EFX | C6: Equifax | D6: consumer, workforce, and verification data
B7: VRSK | C7: Verisk Analytics | D7: insurance, risk, and analytics software
B8: SPGI | C8: S&P Global | D8: market intelligence, ratings, and benchmarks
B9: MCO | C9: Moody's | D9: ratings, data, and research
B10: MSCI | C10: MSCI | D10: index, risk, and portfolio analytics

Sheet Market_Data
B2: Market Data & LTM Metrics ($mm, except share price and multiples)
B3: Ticker | C3: Company | D3: Share Price | E3: Shares Out. (mm) | F3: Market Cap | G3: Debt | H3: Cash | I3: Enterprise Value | J3: LTM Revenue | K3: LTM EBITDA | L3: LTM EBIT | M3: LTM Net Income | N3: EV / Revenue | O3: EV / EBITDA | P3: EV / EBIT | Q3: P / E
B4: MORN | C4: Morningstar | D4: 169.7 | E4: 39.6 | F4: 6717.4 | G4: 1072.6 | H4: 474.5 | I4: 7315.5 | J4: 2445.5 | K4: 716.5 | L4: 526.6 | M4: 374.2 | N4: 2.99 | O4: 10.21 | P4: 13.89 | Q4: 17.95
B5: TRU | C5: TransUnion | D5: 68.79 | E5: 192.6 | F5: 13249 | G5: 5035.9 | H5: 853.6 | I5: 17431.3 | J5: 4576.3 | K5: 1432.6 | L5: 857.8 | M5: 469.9 | N5: 3.81 | O5: 12.17 | P5: 20.32 | Q5: 28.2
B6: EFX | C6: Equifax | D6: 179.66 | E6: 120.3 | F6: 21607.7 | G6: 4055.3 | H6: 180.8 | I6: 25482.2 | J6: 6074.5 | K6: 1822.1 | L6: 1095.2 | M6: 664.3 | N6: 4.19 | O6: 13.99 | P6: 23.27 | Q6: 32.53
B7: VRSK | C7: Verisk Analytics | D7: 183.5 | E7: 137.9 | F7: 25312.3 | G7: 499.4 | H7: 2178.2 | I7: 23633.5 | J7: 3072.7 | K7: 1603.1 | L7: 1343.9 | M7: 908.3 | N7: 7.69 | O7: 14.74 | P7: 17.59 | Q7: 27.87
B8: SPGI | C8: S&P Global | D8: 425.17 | E8: 298.8 | F8: 127040.8 | G8: 12370 | H8: 1745 | I8: 137665.8 | J8: 15336 | K8: 7657 | L8: 6478 | M8: 4820 | N8: 8.98 | O8: 17.98 | P8: 21.25 | Q8: 26.36
B9: MCO | C9: Moody's | D9: 438.78 | E9: 177.3 | F9: 77795.7 | G9: 6994 | H9: 2384 | I9: 82405.7 | J9: 7718 | K9: 3831 | L9: 3351 | M9: 2462 | N9: 10.68 | O9: 21.51 | P9: 24.59 | Q9: 31.6
B10: MSCI | C10: MSCI | D10: 536.9 | E10: 73.5 | F10: 39448.2 | G10: 6202.3 | H10: 515.3 | I10: 45135.2 | J10: 3134.5 | K10: 1737 | L10: 1713.6 | M10: 1202.3 | N10: 14.4 | O10: 25.98 | P10: 26.34 | Q10: 32.81

Sheet Output
B2: Presentation Summary
B4: Metric | C4: Min | D4: 25th %ile | E4: Median | F4: Mean | G4: 75th %ile | H4: Max
B5: EV / Revenue | C5: =MIN(Market_Data!N5:N11) | D5: =QUARTILE.INC(Market_Data!N5:N11,1) | E5: =MEDIAN(Market_Data!N5:N11) | F5: =AVERAGE(Market_Data!N5:N11) | G5: =QUARTILE.INC(Market_Data!N5:N11,3) | H5: =MAX(Market_Data!N5:N11)
B6: EV / EBITDA | C6: =MIN(Market_Data!O5:O11) | D6: =QUARTILE.INC(Market_Data!O5:O11,1) | E6: =MEDIAN(Market_Data!O5:O11) | F6: =AVERAGE(Market_Data!O5:O11) | G6: =QUARTILE.INC(Market_Data!O5:O11,3) | H6: =MAX(Market_Data!O5:O11)
B7: EV / EBIT | C7: =MIN(Market_Data!P5:P11) | D7: =QUARTILE.INC(Market_Data!P5:P11,1) | E7: =MEDIAN(Market_Data!P5:P11) | F7: =AVERAGE(Market_Data!P5:P11) | G7: =QUARTILE.INC(Market_Data!P5:P11,3) | H7: =MAX(Market_Data!P5:P11)
B8: P / E | C8: =MIN(Market_Data!Q5:Q11) | D8: =QUARTILE.INC(Market_Data!Q5:Q11,1) | E8: =MEDIAN(Market_Data!Q5:Q11) | F8: =AVERAGE(Market_Data!Q5:Q11) | G8: =QUARTILE.INC(Market_Data!Q5:Q11,3) | H8: =MAX(Market_Data!Q5:Q11)

Sheet Checks
B2: Checks & Audit
B4: Check | C4: Status
B5: All peer share prices are populated | C5: =IF(COUNT(Market_Data!D5:D11)=7,"OK","CHECK")
B6: Enterprise values are positive | C6: =IF(MIN(Market_Data!I5:I11)>0,"OK","CHECK")
B7: Median EV / EBITDA is available | C7: =IF(ISNUMBER(Output!E6),"OK","CHECK")

Sheet Source_Notes
B2: Source Notes
B4: Category | C4: Entity | D4: Document | E4: As of | F4: URL | G4: Local File | H4: Notes
B5: Public Company | C5: TransUnion | D5: 2025 10-K | E5: 2025-12-31 | F5: https://www.sec.gov/Archives/edgar/data/1552033/000155203326000012/tru-20251231.htm | G5: data/raw/reference_html/tru_2025_10k.html | H5: Primary annual filing used for LTM operating and balance-sheet data.
B6: Public Company | C6: Equifax | D6: 2025 10-K | E6: 2025-12-31 | F6: https://www.sec.gov/Archives/edgar/data/33185/000003318526000010/efx-20251231.htm | G6: data/raw/reference_html/efx_2025_10k.html | H6: Primary annual filing used for LTM operating and balance-sheet data.
B7: Public Company | C7: Verisk Analytics | D7: 2025 10-K | E7: 2025-12-31 | F7: https://www.sec.gov/Archives/edgar/data/1442145/000143774926004452/vrsk20251231_10k.htm | G7: data/raw/reference_html/vrsk_2025_10k.html | H7: Primary annual filing used for LTM operating and balance-sheet data.
B8: Public Company | C8: Morningstar | D8: 2025 10-K | E8: 2025-12-31 | F8: https://www.sec.gov/Archives/edgar/data/1289419/000128941926000013/morn-20251231.htm | G8: data/raw/reference_html/morn_2025_10k.html | H8: Primary annual filing used for LTM operating and balance-sheet data.
B9: Public Company | C9: MSCI | D9: 2025 10-K | E9: 2025-12-31 | F9: https://www.sec.gov/Archives/edgar/data/1408198/000140819826000011/msci-20251231.htm | G9: data/raw/reference_html/msci_2025_10k.html | H9: Primary annual filing used for LTM operating and balance-sheet data.
B10: Public Company | C10: Moody's | D10: 2025 10-K | E10: 2025-12-31 | F10: https://www.sec.gov/Archives/edgar/data/1059556/000162828026009136/mco-20251231.htm | G10: data/raw/reference_html/mco_2025_10k.html | H10: Primary annual filing used for LTM operating and balance-sheet data.
B11: Public Company | C11: S&P Global | D11: 2025 10-K | E11: 2025-12-31 | F11: https://www.sec.gov/Archives/edgar/data/64040/000006404026000013/spgi-20251231.htm | G11: data/raw/reference_html/spgi_2025_10k.html | H11: Primary annual filing used for LTM operating and balance-sheet data.
