Workbook

Sheet Cover
B2: Hypothetical Accretion / Dilution Model | Full Track
B5: Illustrative strategic acquisition case: S&P Global as buyer, TransUnion as target.
B7: • This workbook is hypothetical and meant for merger-model mechanics, not live deal commentary.
B8: • The case focuses on consideration mix, pro forma EPS, synergies, and financing drag.
B9: • The output is built to mirror a timed accretion / dilution interview exercise.

Sheet Instructions
B2: Build Sequence
B4: 1 | C4: Audit buyer and target standalone stats first.
B6: 2 | C6: Build the deal structure and financing bridge before computing pro forma EPS.
B8: 3 | C8: Use Sensitivities to test premium and synergy assumptions against EPS accretion / dilution.

Sheet Assumptions
B2: Deal Assumptions
B4: Buyer | C4: SPGI
B5: Target | C5: TRU
B6: Target Share Price | C6: 68.79
B7: Offer Premium | C7: 0.16
B8: Offer Price | C8: =C6*(1+C7)
B9: Target Shares (mm) | C9: 192.6
B10: Cash Mix | C10: 0.6
B11: Stock Mix | C11: =1-C10
B12: Buyer Share Price | C12: 425.17
B13: New Debt Rate | C13: 0.0575
B14: Tax Rate | C14: 0.25
B15: Cost Synergies ($mm, pre-tax) | C15: 150

Sheet Buyer
B2: S&P Global Standalone Snapshot
B4: Share Price | C4: 425.17
B5: Shares Outstanding (mm) | C5: 298.8
B6: Market Cap ($mm) | C6: 127040.8
B7: Debt ($mm) | C7: 12370
B8: Cash ($mm) | C8: 1745
B9: Enterprise Value ($mm) | C9: 137665.8
B10: LTM Revenue ($mm) | C10: 15336
B11: LTM EBITDA ($mm) | C11: 7657
B12: LTM Net Income ($mm) | C12: 4820
B13: Standalone EPS | C13: =C12/C5

Sheet Target
B2: TransUnion Standalone Snapshot
B4: Share Price | C4: 68.79
B5: Shares Outstanding (mm) | C5: 192.6
B6: Market Cap ($mm) | C6: 13249
B7: Debt ($mm) | C7: 5035.9
B8: Cash ($mm) | C8: 853.6
B9: Enterprise Value ($mm) | C9: 17431.3
B10: LTM Revenue ($mm) | C10: 4576.3
B11: LTM EBITDA ($mm) | C11: 1432.6
B12: LTM Net Income ($mm) | C12: 469.9
B13: Standalone EPS | C13: =C12/C5

Sheet Deal_Structure
B2: Deal Structure ($mm unless noted)
B4: Offer Price | C4: =Assumptions!C8
B5: Target Shares (mm) | C5: =Assumptions!C9
B6: Equity Purchase Price | C6: =C4*C5
B7: Target Debt Assumed | C7: =Target!C7
B8: Less: Target Cash | C8: =Target!C8
B9: Implied Enterprise Value | C9: =C6+C7-C8
B10: Cash Consideration | C10: =C6*Assumptions!C10
B11: Stock Consideration | C11: =C6*Assumptions!C11
B12: Buyer Shares Issued (mm) | C12: =C11/Assumptions!C12
B13: New Debt Raised | C13: =C10
B14: Exchange Ratio | C14: =C12/Assumptions!C9

Sheet Accretion_Dilution
B2: Pro Forma EPS Bridge
B4: Buyer Standalone Net Income | C4: =Buyer!C12
B5: Target Net Income | C5: =Target!C12
B6: After-Tax Synergies | C6: =Assumptions!C15*(1-Assumptions!C14)
B7: After-Tax Financing Drag | C7: =Deal_Structure!C13*Assumptions!C13*(1-Assumptions!C14)
B8: Pro Forma Net Income | C8: =SUM(C4:C6)-C7
B9: Buyer Shares Outstanding (mm) | C9: =Buyer!C5
B10: Shares Issued (mm) | C10: =Deal_Structure!C12
B11: Pro Forma Shares (mm) | C11: =SUM(C9:C10)
B12: Buyer Standalone EPS | C12: =Buyer!C13
B13: Pro Forma EPS | C13: =C8/C11
B14: Accretion / (Dilution) | C14: =C13/C12-1

Sheet Sensitivities
B2: EPS Accretion / (Dilution) Sensitivity
D4: 0.15 | E4: 0.2 | F4: 0.25 | G4: 0.3 | H4: 0.35
B5: 75 | D5: -0.019662281 | E5: -0.024996229 | F5: -0.030309028 | G5: -0.035600805 | H5: -0.040871683
B6: 100 | D6: -0.015950314 | E6: -0.021291635 | F6: -0.026611778 | G6: -0.031910869 | H6: -0.037189034
B7: 150 | D7: -0.0085263787 | E7: -0.013882446 | F7: -0.019217277 | G7: -0.024530999 | H7: -0.029823736
B8: 200 | D8: -0.0011024436 | E8: -0.0064732573 | F8: -0.011822777 | G8: -0.017151128 | H8: -0.022458437
B9: 250 | D9: 0.0063214914 | E9: 0.00093593127 | F9: -0.0044282762 | G9: -0.0097712576 | H9: -0.015093139

Sheet Output
B2: Merger Model Output
B4: Offer Price | C4: =Deal_Structure!C4
B5: Premium | C5: =Assumptions!C7
B6: Implied Enterprise Value | C6: =Deal_Structure!C9
B7: Pro Forma EPS | C7: =Accretion_Dilution!C13
B8: Accretion / (Dilution) | C8: =Accretion_Dilution!C14

Sheet Checks
B2: Checks & Audit
B4: Check | C4: Status
B5: Cash and stock mix sum to 100% | C5: =IF(ABS(Assumptions!C10+Assumptions!C11-1)<0.0001,"OK","CHECK")
B6: Shares issued is positive | C6: =IF(Deal_Structure!C12>0,"OK","CHECK")
B7: Pro forma EPS is numeric | C7: =IF(ISNUMBER(Accretion_Dilution!C13),"OK","CHECK")
B8: Sensitivity grid is populated | C8: =IF(COUNT(Sensitivities!D5:H9)=25,"OK","CHECK")

Sheet Source_Notes
B2: Source Notes
B4: Category | C4: Entity | D4: Document | E4: As of | F4: URL | G4: Local File | H4: Notes
B5: Public Company | C5: TransUnion | D5: 2025 10-K | E5: 2025-12-31 | F5: https://www.sec.gov/Archives/edgar/data/1552033/000155203326000012/tru-20251231.htm | G5: data/raw/reference_html/tru_2025_10k.html | H5: Primary annual filing used for LTM operating and balance-sheet data.
B6: Public Company | C6: Equifax | D6: 2025 10-K | E6: 2025-12-31 | F6: https://www.sec.gov/Archives/edgar/data/33185/000003318526000010/efx-20251231.htm | G6: data/raw/reference_html/efx_2025_10k.html | H6: Primary annual filing used for LTM operating and balance-sheet data.
B7: Public Company | C7: Verisk Analytics | D7: 2025 10-K | E7: 2025-12-31 | F7: https://www.sec.gov/Archives/edgar/data/1442145/000143774926004452/vrsk20251231_10k.htm | G7: data/raw/reference_html/vrsk_2025_10k.html | H7: Primary annual filing used for LTM operating and balance-sheet data.
B8: Public Company | C8: Morningstar | D8: 2025 10-K | E8: 2025-12-31 | F8: https://www.sec.gov/Archives/edgar/data/1289419/000128941926000013/morn-20251231.htm | G8: data/raw/reference_html/morn_2025_10k.html | H8: Primary annual filing used for LTM operating and balance-sheet data.
B9: Public Company | C9: MSCI | D9: 2025 10-K | E9: 2025-12-31 | F9: https://www.sec.gov/Archives/edgar/data/1408198/000140819826000011/msci-20251231.htm | G9: data/raw/reference_html/msci_2025_10k.html | H9: Primary annual filing used for LTM operating and balance-sheet data.
B10: Public Company | C10: Moody's | D10: 2025 10-K | E10: 2025-12-31 | F10: https://www.sec.gov/Archives/edgar/data/1059556/000162828026009136/mco-20251231.htm | G10: data/raw/reference_html/mco_2025_10k.html | H10: Primary annual filing used for LTM operating and balance-sheet data.
B11: Public Company | C11: S&P Global | D11: 2025 10-K | E11: 2025-12-31 | F11: https://www.sec.gov/Archives/edgar/data/64040/000006404026000013/spgi-20251231.htm | G11: data/raw/reference_html/spgi_2025_10k.html | H11: Primary annual filing used for LTM operating and balance-sheet data.
B12: Precedent Transaction | C12: Dun & Bradstreet Holdings | D12: Announcement Press Release | E12: 2025-03-24 | F12: https://www.sec.gov/Archives/edgar/data/1799208/000110465925027293/tm2510133d1_ex99-1.htm | G12: data/raw/reference_html/dnb_announcement_press_release.html | H12: Public announcement material used for offer price and buyer context.
B13: Precedent Transaction | C13: Dun & Bradstreet Holdings | D13: Premium Reference | E13: 2025-03-24 | F13: https://www.investing.com/news/stock-market-news/pe-firm-clearlake-to-buy-dun--bradstreet-for-41-billion-in-cash-3945178 | H13: Public source documenting the premium basis noted in the workbook.
B14: Precedent Transaction | C14: Envestnet | D14: Announcement Press Release | E14: 2024-07-11 | F14: https://www.stocktitan.net/news/ENV/envestnet-leading-wealth-technology-platform-announces-4-5-billion-i21lo25fnrhh.html | G14: data/raw/reference_html/env_announcement_press_release.html | H14: Public announcement material used for offer price and buyer context.
B15: Precedent Transaction | C15: Envestnet | D15: Premium Reference | E15: 2024-07-11 | F15: https://citywire.com/ria/news/bain-capital-to-take-envestnet-private-in-4-5bn-deal/a2442550 | G15: data/raw/reference_html/env_premium_reference.html | H15: Public source documenting the premium basis noted in the workbook.
B16: Precedent Transaction | C16: Model N | D16: Announcement Press Release | E16: 2024-04-08 | F16: https://marketchameleon.com/PressReleases/i/1874156/MODN/model-n-to-be-acquired-by-vista | G16: data/raw/reference_html/modn_announcement_press_release.html | H16: Public announcement material used for offer price and buyer context.
B17: Precedent Transaction | C17: Model N | D17: Premium Reference | E17: 2024-04-08 | F17: https://www.benzinga.com/markets/equities/24/04/38144970/why-information-technology-model-n-shares-are-surging-today | G17: data/raw/reference_html/modn_premium_reference.html | H17: Public source documenting the premium basis noted in the workbook.
B18: Precedent Transaction | C18: Black Knight | D18: Announcement Press Release | E18: 2022-05-04 | F18: https://www.nasdaq.com/articles/intercontinental-exchange-to-buy-black-knight-in-%2413.1-bln-deal | H18: Public announcement material used for offer price and buyer context.
B19: Precedent Transaction | C19: Black Knight | D19: Premium Reference | E19: 2022-05-04 | F19: https://www.jaxdailyrecord.com/news/2022/may/12/low-stock-price-spurred-black-knight-deal/ | G19: data/raw/reference_html/bki_premium_reference.html | H19: Public source documenting the premium basis noted in the workbook.
B20: Precedent Transaction | C20: Bottomline Technologies | D20: Announcement Press Release | E20: 2021-12-17 | F20: https://marketchameleon.com/PressReleases/i/1352182/EPAY/bottomline-to-be-acquired-by-thoma-bravo | G20: data/raw/reference_html/epay_announcement_press_release.html | H20: Public announcement material used for offer price and buyer context.
B21: Precedent Transaction | C21: Bottomline Technologies | D21: Premium Reference | E21: 2021-12-17 | F21: https://www.publicnow.com/view/6F71E0380357D4D65D2A238C7AB87A88E3B4D5A6?1652450101= | H21: Public source documenting the premium basis noted in the workbook.
B22: DCF | C22: TransUnion | D22: 2025 10-K | E22: 2025-12-31 | F22: https://www.sec.gov/Archives/edgar/data/1552033/000155203326000012/tru-20251231.htm | G22: data/raw/reference_html/tru_2025_10k.html | H22: Historical actuals and balance-sheet data.
B23: DCF | C23: TransUnion | D23: 2026 Earnings Release | E23: 2026-02-12 | F23: https://www.sec.gov/Archives/edgar/data/1552033/000155203326000006/exhibit99112312025.htm | G23: data/raw/reference_html/tru_2026_guidance.html | H23: Management 2026 revenue and adjusted EBITDA guidance.
B24: Valuation | C24: Damodaran | D24: Implied ERP Update | E24: 2026-04-01 | F24: https://pages.stern.nyu.edu/~adamodar/New_Home_Page/home.htm | G24: data/raw/reference_html/damodaran_home_apr_2026.html | H24: Used for U.S. ERP and risk-free rate assumptions.
