Workbook

Sheet Cover
B2: Investment Banking Workflow: 3-Statement Model Build
B5: TRU historicals with a streamlined forecast case that mirrors a real analyst workflow.
B7: • The model separates assumptions, statements, schedules, summary outputs, and checks.
B8: • Forecasts roll through the income statement, selected balance-sheet lines, and cash build.
B9: • This workbook intentionally bridges into the full DCF module.

Sheet Instructions
B2: Build Sequence
B4: 1 | C4: Start on Assumptions and confirm the forecast driver set.
B6: 2 | C6: Link the income statement first, then roll the operating schedules and summary outputs.
B8: 3 | C8: Use Summary for management-ready outputs and Checks for audit control.

Sheet Assumptions
B2: Forecast Drivers
D4: 2026 | E4: 2027 | F4: 2028
B5: Revenue Growth | D5: 0.085 | E5: 0.07 | F5: 0.06
B6: EBITDA Margin | D6: 0.315 | E6: 0.318 | F6: 0.32
B7: D&A Margin | D7: 0.12 | E7: 0.117 | F7: 0.114
B8: Capex Margin | D8: 0.07 | E8: 0.067 | F8: 0.065
B9: NWC Margin | D9: 0.094 | E9: 0.093 | F9: 0.092

Sheet IS
B2: Income Statement ($mm)
D4: 2023 | E4: 2024 | F4: 2025 | G4: 2026 | H4: 2027 | I4: 2028
B5: Revenue | D5: 3831.2 | E5: 4183.8 | F5: 4576.3 | G5: =F5*(1+Assumptions!G5) | H5: =G5*(1+Assumptions!H5) | I5: =H5*(1+Assumptions!I5)
B6: EBITDA | D6: 652.9 | E6: 1204.5 | F6: 1432.6 | G6: =G5*Assumptions!G6 | H6: =H5*Assumptions!H6 | I6: =I5*Assumptions!I6
B7: D&A | D7: 524.4 | E7: 537.8 | F7: 574.8 | G7: =G5*Assumptions!G7 | H7: =H5*Assumptions!H7 | I7: =I5*Assumptions!I7
B8: EBIT | D8: 128.5 | E8: 666.7 | F8: 857.8 | G8: =G6-G7 | H8: =H6-H7 | I8: =I6-I7
B9: Interest | D9: 288.2 | E9: 265.2 | F9: 235.8 | G9: =F9 | H9: =F9 | I9: =F9
B10: Pretax Income | D10: -159.7 | E10: 401.5 | F10: 622 | G10: =G8-G9 | H10: =H8-H9 | I10: =I8-I9
B11: Taxes | D11: -39.925 | E11: 100.375 | F11: 155.5 | G11: =G10*0.25 | H11: =H10*0.25 | I11: =I10*0.25
B12: Net Income | D12: -190.8 | E12: 302.3 | F12: 469.9 | G12: =G10-G11 | H12: =H10-H11 | I12: =I10-I11

Sheet Schedules
B2: Operating Support Schedules ($mm)
D4: 2023 | E4: 2024 | F4: 2025 | G4: 2026 | H4: 2027 | I4: 2028
B5: NWC | D5: 405.4 | E5: 388.6 | F5: 441.8 | G5: =IS!G5*Assumptions!G9 | H5: =IS!H5*Assumptions!H9 | I5: =IS!I5*Assumptions!I9
B6: Change in NWC | D6: 0 | E6: -16.8 | F6: 53.2 | G6: =G5-F5 | H6: =H5-G5 | I6: =I5-H5
B7: Capex | D7: 310.7 | E7: 315.8 | F7: 326 | G7: =IS!G5*Assumptions!G8 | H7: =IS!H5*Assumptions!H8 | I7: =IS!I5*Assumptions!I8
B8: FCF Before Financing | D8: 22.9 | E8: 541.1 | F8: 665.5 | G8: =IS!G12+IS!G7-G7-G6 | H8: =IS!H12+IS!H7-H7-H6 | I8: =IS!I12+IS!I7-I7-I6

Sheet Summary
B2: Analyst Summary
B4: 2026 Revenue | C4: =IS!G5
B5: 2026 EBITDA | C5: =IS!G6
B6: 2026 Net Income | C6: =IS!G12
B7: 2028 FCF Before Financing | C7: =Schedules!I8

Sheet Checks
B2: Checks & Audit
B4: Check | C4: Status
B5: 2026 revenue flows from assumptions | C5: =IF(ABS(IS!G5-(IS!F5*(1+Assumptions!G5)))<0.1,"OK","CHECK")
B6: FCF before financing is positive by 2028 | C6: =IF(Schedules!I8>0,"OK","CHECK")
B7: Net income line is populated for forecast years | C7: =IF(COUNT(IS!G12:I12)=3,"OK","CHECK")

Sheet Source_Notes
B2: Source Notes
B4: Category | C4: Entity | D4: Document | E4: As of | F4: URL | G4: Local File | H4: Notes
B5: DCF | C5: TransUnion | D5: 2025 10-K | E5: 2025-12-31 | F5: https://www.sec.gov/Archives/edgar/data/1552033/000155203326000012/tru-20251231.htm | G5: data/raw/reference_html/tru_2025_10k.html | H5: Historical actuals and balance-sheet data.
B6: DCF | C6: TransUnion | D6: 2026 Earnings Release | E6: 2026-02-12 | F6: https://www.sec.gov/Archives/edgar/data/1552033/000155203326000006/exhibit99112312025.htm | G6: data/raw/reference_html/tru_2026_guidance.html | H6: Management 2026 revenue and adjusted EBITDA guidance.
B7: Valuation | C7: Damodaran | D7: Implied ERP Update | E7: 2026-04-01 | F7: https://pages.stern.nyu.edu/~adamodar/New_Home_Page/home.htm | G7: data/raw/reference_html/damodaran_home_apr_2026.html | H7: Used for U.S. ERP and risk-free rate assumptions.
